Metadata-Version: 2.1
Name: check-digit-EAN13
Version: 0.2
Summary: A simple library to get check digit
Home-page: UNKNOWN
Author: Muhammed gassali
Author-email: mhdgassalishalu5554@gmail.com
License: MIT
Keywords: check-digit
Platform: UNKNOWN
Classifier: Development Status :: 5 - Production/Stable
Classifier: Intended Audience :: Education
Classifier: Operating System :: Microsoft :: Windows :: Windows 10
Classifier: License :: OSI Approved :: MIT License
Classifier: Programming Language :: Python :: 2.7
Classifier: Programming Language :: Python :: 3
Classifier: Programming Language :: Python :: 3.5
Classifier: Programming Language :: Python :: 3.6
Classifier: Programming Language :: Python :: 3.7
Classifier: Programming Language :: Python :: 3.8
Classifier: Programming Language :: Python :: 3.9
License-File: LICENSE.txt
